pycubexr/__init__.py
pycubexr/classes/__init__.py
pycubexr/classes/cnode.py
pycubexr/classes/location.py
pycubexr/classes/location_group.py
pycubexr/classes/metric.py
pycubexr/classes/metric_values.py
pycubexr/classes/region.py
pycubexr/classes/system_tree_node.py
pycubexr/classes/values.py
pycubexr/parsers/__init__.py
pycubexr/parsers/anchor_xml_parser.py
pycubexr/parsers/data_parser.py
pycubexr/parsers/index_parser.py
pycubexr/parsers/metrics_parser.py
pycubexr/parsers/tar_parser.py
pycubexr/parsers/xml_parser_helper.py
pycubexr/utils/__init__.py
pycubexr/utils/caching.py
pycubexr/utils/custom_tarinfo.py
pycubexr/utils/exceptions.py
pycubexr/utils/logger.py
pycubexr/utils/metric_formats.py
pycubexr-2.1.0.dist-info/licenses/AUTHORS
pycubexr-2.1.0.dist-info/licenses/LICENSE
pycubexr-2.1.0.dist-info/METADATA
pycubexr-2.1.0.dist-info/WHEEL
pycubexr-2.1.0.dist-info/top_level.txt
pycubexr-2.1.0.dist-info/RECORD
